docxbuilder/__init__.py
docxbuilder/builder.py
docxbuilder/highlight.py
docxbuilder/writer.py
docxbuilder/docx/__init__.py
docxbuilder/docx/docx.py
docxbuilder/docx/style.docx
docxbuilder-1.2.0.dist-info/LICENSE
docxbuilder-1.2.0.dist-info/METADATA
docxbuilder-1.2.0.dist-info/WHEEL
docxbuilder-1.2.0.dist-info/top_level.txt
docxbuilder-1.2.0.dist-info/RECORD
