Metadata-Version: 2.1
Name: docxbuilder
Version: 1.2.0
Summary: Sphinx docx builder extension
Home-page: https://github.com/amedama41/docxbuilder
Author: amedama41
Author-email: kamo.devel41@gmail.com
License: UNKNOWN
Keywords: sphinx,extension,docx,OpenXML
Platform: UNKNOWN
Classifier: Framework :: Sphinx :: Extension
Classifier: License :: OSI Approved :: MIT License
Classifier: Programming Language :: Python :: 2.7
Classifier: Programming Language :: Python :: 3
Classifier: Topic :: Documentation :: Sphinx
Requires-Python: >=2.7,!=3.0.*,!=3.1.*,!=3.2.*,!=3.3.*,!=3.4.*
Provides-Extra: math
